dynamic/__init__.py
dynamic/dynamic_loader.py
dynamic/source_grabbers.py
python_dynamic_loader-1.1.0.dist-info/LICENSE
python_dynamic_loader-1.1.0.dist-info/METADATA
python_dynamic_loader-1.1.0.dist-info/WHEEL
python_dynamic_loader-1.1.0.dist-info/top_level.txt
python_dynamic_loader-1.1.0.dist-info/RECORD
